unit_converter_mcp/__init__.py
unit_converter_mcp/server.py
unit_converter_mcp/prompts/__init__.py
unit_converter_mcp/resources/units.json
unit_converter_mcp/tools/__init__.py
unit_converter_mcp/tools/angle.py
unit_converter_mcp/tools/area.py
unit_converter_mcp/tools/batch.py
unit_converter_mcp/tools/computer.py
unit_converter_mcp/tools/density.py
unit_converter_mcp/tools/energy.py
unit_converter_mcp/tools/force.py
unit_converter_mcp/tools/length.py
unit_converter_mcp/tools/mass.py
unit_converter_mcp/tools/power.py
unit_converter_mcp/tools/pressure.py
unit_converter_mcp/tools/speed.py
unit_converter_mcp/tools/temperature.py
unit_converter_mcp/tools/time.py
unit_converter_mcp/tools/volume.py
unit_converter_mcp/utils/__init__.py
unit_converter_mcp/utils/validation.py
unit_converter_mcp-0.1.2.dist-info/METADATA
unit_converter_mcp-0.1.2.dist-info/WHEEL
unit_converter_mcp-0.1.2.dist-info/entry_points.txt
unit_converter_mcp-0.1.2.dist-info/licenses/LICENSE
unit_converter_mcp-0.1.2.dist-info/RECORD
